setup.py
qcbacktester/__init__.py
qcbacktester.egg-info/PKG-INFO
qcbacktester.egg-info/SOURCES.txt
qcbacktester.egg-info/dependency_links.txt
qcbacktester.egg-info/not-zip-safe
qcbacktester.egg-info/top_level.txt