Metadata-Version: 1.0
Name: qcbacktester
Version: 0.1
Summary: The qcbacktester is the high performance trading engine that runs behind quantcollab
Home-page: http://github.com/ishandutta2007/qcbacktester
Author: Ishan
Author-email: ishandutta2007@gmail.com
License: MIT
Platform: UNKNOWN
